alibabacloud_tea_openapi/__init__.py
alibabacloud_tea_openapi/client.py
alibabacloud_tea_openapi/sm3.py
alibabacloud_tea_openapi/utils.py
alibabacloud_tea_openapi/exceptions/__init__.py
alibabacloud_tea_openapi/exceptions/_alibaba_cloud.py
alibabacloud_tea_openapi/exceptions/_client.py
alibabacloud_tea_openapi/exceptions/_server.py
alibabacloud_tea_openapi/exceptions/_throttling.py
alibabacloud_tea_openapi/models/__init__.py
alibabacloud_tea_openapi/models/_sseresponse.py
alibabacloud_tea_openapi/utils_models/__init__.py
alibabacloud_tea_openapi/utils_models/_config.py
alibabacloud_tea_openapi/utils_models/_global_parameters.py
alibabacloud_tea_openapi/utils_models/_open_api_request.py
alibabacloud_tea_openapi/utils_models/_params.py
alibabacloud_tea_openapi-0.4.1.dist-info/METADATA
alibabacloud_tea_openapi-0.4.1.dist-info/WHEEL
alibabacloud_tea_openapi-0.4.1.dist-info/top_level.txt
alibabacloud_tea_openapi-0.4.1.dist-info/RECORD
