Metadata-Version: 2.1
Name: alibabacloud-tea-openapi
Version: 0.4.1
Summary: Alibaba Cloud openapi SDK Library for Python
Home-page: https://github.com/aliyun/darabonba-openapi
Author: Alibaba Cloud SDK
Author-email: sdk-team@alibabacloud.com
License: Apache License 2.0
Keywords: alibabacloud,tea,openapi
Platform: any
Classifier: Development Status :: 4 - Beta
Classifier: Intended Audience :: Developers
Classifier: License :: OSI Approved :: Apache Software License
Classifier: Programming Language :: Python
Classifier: Programming Language :: Python :: 3
Classifier: Programming Language :: Python :: 3.7
Classifier: Programming Language :: Python :: 3.8
Classifier: Programming Language :: Python :: 3.9
Classifier: Programming Language :: Python :: 3.10
Classifier: Programming Language :: Python :: 3.11
Classifier: Programming Language :: Python :: 3.12
Classifier: Topic :: Software Development
Requires-Python: >=3.7
